README.rst
setup.py
RadiusLibrary/__init__.py
RadiusLibrary/radiuslibrary.py
robotframework_radius.egg-info/PKG-INFO
robotframework_radius.egg-info/SOURCES.txt
robotframework_radius.egg-info/dependency_links.txt
robotframework_radius.egg-info/pbr.json
robotframework_radius.egg-info/requires.txt
robotframework_radius.egg-info/top_level.txt