Metadata-Version: 1.1
Name: robotframework-radius
Version: 0.2.3
Summary: Robotframework RADIUS library
Home-page: https://github.com/deviousops/robotframework-radius
Author: Michael van Slingerland
Author-email: michael@deviousops.nl
License: UNKNOWN
Download-URL: https://github.com/deviousops/robotframework-radius/archive/0.2.3.tar.gz
Platform: UNKNOWN
Classifier: License :: OSI Approved :: Apache Software License
